gsheetstools/__init__.py
gsheetstools/helpers.py
g_sheets_tools-0.1.9.dist-info/LICENSE
g_sheets_tools-0.1.9.dist-info/WHEEL
g_sheets_tools-0.1.9.dist-info/METADATA
g_sheets_tools-0.1.9.dist-info/RECORD
