Metadata-Version: 2.1
Name: g-sheets-tools
Version: 0.1.9
Summary: 
Home-page: https://github.com/afriedman412/g-sheets-tools
Author: Andy Friedman
Author-email: afriedman412@gmail.com
Requires-Python: >=3.8.5,<4.0.0
Classifier: Programming Language :: Python :: 3
Classifier: Programming Language :: Python :: 3.10
Classifier: Programming Language :: Python :: 3.9
Requires-Dist: cachetools (==4.1.1)
Requires-Dist: certifi (>=2021.10.8,<2022.0.0)
Requires-Dist: chardet (>=4.0.0,<5.0.0)
Requires-Dist: google-api-core (>=2.3.2,<3.0.0)
Requires-Dist: google-api-python-client (>=2.33.0,<3.0.0)
Requires-Dist: google-auth (>=2.3.3,<3.0.0)
Requires-Dist: google-auth-httplib2 (>=0.1.0,<0.2.0)
Requires-Dist: google-auth-oauthlib (>=0.4.6,<0.5.0)
Requires-Dist: googleapis-common-protos (>=1.54.0,<2.0.0)
Requires-Dist: httplib2 (>=0.20.2,<0.21.0)
Requires-Dist: idna (>=3.3,<4.0)
Requires-Dist: numpy (>=1.19.2,<2.0.0)
Requires-Dist: oauthlib (>=3.1.1,<4.0.0)
Requires-Dist: pandas (>=1.3.5,<2.0.0)
Requires-Dist: protobuf (>=3.19.1,<4.0.0)
Requires-Dist: pyasn1 (>=0.4.8,<0.5.0)
Requires-Dist: pyasn1-modules (>=0.2.8,<0.3.0)
Requires-Dist: python-dateutil (>=2.8.2,<3.0.0)
Requires-Dist: pytz (>=2021.3,<2022.0)
Requires-Dist: requests (>=2.26.0,<3.0.0)
Requires-Dist: requests-oauthlib (>=1.3.0,<2.0.0)
Requires-Dist: rsa (>=4.8,<5.0)
Requires-Dist: six (>=1.16.0,<2.0.0)
Requires-Dist: uritemplate (>=4.1.1,<5.0.0)
Requires-Dist: urllib3 (>=1.26.7,<2.0.0)
Project-URL: Repository, https://github.com/afriedman412/g-sheets-tools
